cdktf_cdktf_provider_oraclepaas/__init__.py
cdktf_cdktf_provider_oraclepaas/py.typed
cdktf_cdktf_provider_oraclepaas/_jsii/__init__.py
cdktf_cdktf_provider_oraclepaas/_jsii/provider-oraclepaas@8.0.1.jsii.tgz
cdktf_cdktf_provider_oraclepaas/application_container/__init__.py
cdktf_cdktf_provider_oraclepaas/data_oraclepaas_database_service_instance/__init__.py
cdktf_cdktf_provider_oraclepaas/database_access_rule/__init__.py
cdktf_cdktf_provider_oraclepaas/database_service_instance/__init__.py
cdktf_cdktf_provider_oraclepaas/java_access_rule/__init__.py
cdktf_cdktf_provider_oraclepaas/java_service_instance/__init__.py
cdktf_cdktf_provider_oraclepaas/mysql_access_rule/__init__.py
cdktf_cdktf_provider_oraclepaas/mysql_service_instance/__init__.py
cdktf_cdktf_provider_oraclepaas/provider/__init__.py
cdktf_cdktf_provider_oraclepaas-8.0.1.dist-info/LICENSE
cdktf_cdktf_provider_oraclepaas-8.0.1.dist-info/METADATA
cdktf_cdktf_provider_oraclepaas-8.0.1.dist-info/WHEEL
cdktf_cdktf_provider_oraclepaas-8.0.1.dist-info/top_level.txt
cdktf_cdktf_provider_oraclepaas-8.0.1.dist-info/RECORD
